so_pysm_models/__init__.py
so_pysm_models/_astropy_init.py
so_pysm_models/alms.py
so_pysm_models/co_lines.py
so_pysm_models/conftest.py
so_pysm_models/dust.py
so_pysm_models/extragalactic.py
so_pysm_models/filter_utils.py
so_pysm_models/laws.py
so_pysm_models/so_models.py
so_pysm_models/synchrotron.py
so_pysm_models/version.py
so_pysm_models/extern/__init__.py
so_pysm_models/tests/__init__.py
so_pysm_models/tests/coveragerc
so_pysm_models/tests/setup_package.py
so_pysm_models/tests/test_alms.py
so_pysm_models/tests/test_cmb.py
so_pysm_models/tests/test_co.py
so_pysm_models/tests/test_dust.py
so_pysm_models/tests/test_extragalactic.py
so_pysm_models/tests/test_so_models.py
so_pysm_models/tests/test_synchrotron.py
so_pysm_models/tests/data/CO10_TQUmaps_noHGL_nside16_ring.fits.zip
so_pysm_models/tests/data/CO10_TQUmaps_wHGL_nside16_ring.fits.zip
so_pysm_models/tests/data/Gaussian_dust_353GHz_uRJ_testmap_ns128.fits.zip
so_pysm_models/tests/data/Gaussian_synch_23GHz_uRJ_testmap_ns128.fits.zip
so_pysm_models/tests/data/Planck_bestfit_alm_seed_583_lmax_120_K_CMB.fits.zip
so_pysm_models/tests/data/Planck_bestfit_alm_seed_583_lmax_95_K_CMB.fits.zip
so_pysm_models/tests/data/fullskyUnlensedUnabberatedCMB_alm_set00_00000.fits.zip
so_pysm_models/tests/data/map_nside_32_from_Planck_bestfit_alm_seed_583_K_CMB.fits.zip
so_pysm_models/tests/data/test_cmb_map.fits.zip
so_pysm_models/utils/__init__.py
so_pysm_models/utils/add_small_scales.py
so_pysm_models/utils/generate_html_directory_index.py
so_pysm_models/utils/rotate_maps.py
so_pysm_models/utils/ud_grade_maps.py
so_pysm_models/utils/tests/__init__.py
so_pysm_models-2.4.0.dist-info/METADATA
so_pysm_models-2.4.0.dist-info/WHEEL
so_pysm_models-2.4.0.dist-info/top_level.txt
so_pysm_models-2.4.0.dist-info/RECORD
